[
        {
                "seqidx": 3538,
                "category": "url",
                "keyword": "korea",
                "url": "htthttp://3bbad7fauom4d6sgppalyqddsqbf5u5p56b5k5uk2zxsy3d6ey2jobad.onion/v/cache?q=nric+malaysia&l=http%3A%2F%2Ftdsrvhos656xypxsqtkqmiwefuvlyqmnvk5faoo23oh2m4xqg4gr47ad.onion%2Fpol%2Fres%2F25931.html&p=9&u=388043182&strip=1&vwsrc=0p",
                "title": "TBD",
                "write_time": "2024-08-20 00:40:45",
                "analysis_flag": "분석 대기",
                "threat_flag": "해킹",
                "response_flag": "대기",
                "threat_log": "TBD"
        },
        {
                "seqidx": 3538,
                "category": "url",
                "keyword": "korea",
                "url": "htthttp://3bbad7fauom4d6sgppalyqddsqbf5u5p56b5k5uk2zxsy3d6ey2jobad.onion/v/cache?q=nric+malaysia&l=http%3A%2F%2Ftdsrvhos656xypxsqtkqmiwefuvlyqmnvk5faoo23oh2m4xqg4gr47ad.onion%2Fpol%2Fres%2F25931.html&p=9&u=388043182&strip=1&vwsrc=0p",
                "title": "TBD",
                "write_time": "2024-08-20 00:40:45",
                "analysis_flag": "분석 대기",
                "threat_flag": "해킹",
                "response_flag": "대기",
                "threat_log": "TBD"
        },
        {
                "seqidx": 3538,
                "category": "url",
                "keyword": "korea",
                "url": "htthttp://3bbad7fauom4d6sgppalyqddsqbf5u5p56b5k5uk2zxsy3d6ey2jobad.onion/v/cache?q=nric+malaysia&l=http%3A%2F%2Ftdsrvhos656xypxsqtkqmiwefuvlyqmnvk5faoo23oh2m4xqg4gr47ad.onion%2Fpol%2Fres%2F25931.html&p=9&u=388043182&strip=1&vwsrc=0p",
                "title": "TBD",
                "write_time": "2024-08-20 00:40:45",
                "analysis_flag": "분석 대기",
                "threat_flag": "해킹",
                "response_flag": "대기",
                "threat_log": "TBD"
        }
]